<package>
  <description brief="face_tracker">

     face_tracker allow simple face detection from an image topic.

  </description>
  <author>Xavier</author>
  <license>BSD</license>
  <review status="unreviewed" notes=""/>
  <url>http://ros.org/wiki/face_tracker</url>
  <depend package="std_msgs"/>
  <depend package="roscpp"/>
  <depend package="sensor_msgs"/>
  <depend package="opencv2"/>
  <depend package="cv_bridge"/>
  <depend package="std_msgs"/>
  <depend package="image_transport"/>
  <depend package="LunarNXT" />
</package>


